mrmd/__init__.py
mrmd/cleanup.py
mrmd/cli.py
mrmd/config.py
mrmd/orchestrator.py
mrmd/processes.py
mrmd/project.py
mrmd/python_runtime.py
mrmd/runtimes.py
mrmd/server.py
mrmd/venv.py
mrmd/venv_discovery.py
mrmd/bundled/.gitkeep
mrmd-0.10.1.dist-info/METADATA
mrmd-0.10.1.dist-info/WHEEL
mrmd-0.10.1.dist-info/entry_points.txt
mrmd-0.10.1.dist-info/RECORD
