Metadata-Version: 2.4
Name: mrmd
Version: 0.10.1
Summary: Collaborative markdown notebooks - edit and run code together
Project-URL: Homepage, https://github.com/maximerivest/mrmd-packages
Project-URL: Repository, https://github.com/maximerivest/mrmd-packages
Author: Maxime
License-Expression: MIT
Keywords: collaborative,crdt,editor,markdown,notebook,yjs
Classifier: Development Status :: 3 - Alpha
Classifier: Environment :: Console
Classifier: Environment :: Web Environment
Classifier: Intended Audience :: Developers
Classifier: License :: OSI Approved :: MIT License
Classifier: Programming Language :: Python :: 3
Classifier: Programming Language :: Python :: 3.11
Classifier: Programming Language :: Python :: 3.12
Classifier: Programming Language :: Python :: 3.13
Classifier: Topic :: Software Development
Classifier: Topic :: Text Editors
Requires-Python: >=3.11
Requires-Dist: fastapi>=0.104.0
Requires-Dist: httpx>=0.25.0
Requires-Dist: mrmd-ai>=0.1.0
Requires-Dist: mrmd-python>=0.2.0
Requires-Dist: nodejs-bin>=18.0.0
Requires-Dist: uvicorn[standard]>=0.24.0
Provides-Extra: ai
Requires-Dist: mrmd-ai>=0.1.0; extra == 'ai'
Provides-Extra: all
Requires-Dist: mrmd-ai>=0.1.0; extra == 'all'
Provides-Extra: dev
Requires-Dist: pytest-asyncio>=0.24.0; extra == 'dev'
Requires-Dist: pytest>=8.0.0; extra == 'dev'
